LICENSE
crosspm/__init__.py
crosspm/__main__.py
crosspm/cmakepm.cmake
crosspm/config.py
crosspm/cpm.py
crosspm/crosspm.cmake
crosspm/adapters/__init__.py
crosspm/adapters/artifactoryaql.py
crosspm/adapters/common.py
crosspm/adapters/files.py
crosspm/helpers/__init__.py
crosspm/helpers/archive.py
crosspm/helpers/cache.py
crosspm/helpers/config.py
crosspm/helpers/content.py
crosspm/helpers/downloader.py
crosspm/helpers/exceptions.py
crosspm/helpers/locker.py
crosspm/helpers/output.py
crosspm/helpers/package.py
crosspm/helpers/parser.py
crosspm/helpers/promoter.py
crosspm/helpers/python.py
crosspm/helpers/source.py
crosspm/helpers/usedby.py
crosspm/template/__init__.py
crosspm/template/all_yaml.j2
crosspm/template/gus.j2
crosspm-1.0.15.12.dist-info/LICENSE
crosspm-1.0.15.12.dist-info/METADATA
crosspm-1.0.15.12.dist-info/WHEEL
crosspm-1.0.15.12.dist-info/entry_points.txt
crosspm-1.0.15.12.dist-info/top_level.txt
crosspm-1.0.15.12.dist-info/RECORD
