Metadata-Version: 2.1
Name: crosspm
Version: 1.0.15.12
Summary: Cross Package Manager
Home-page: http://devopshq.github.io/crosspm
Author: Alexander Kovalev
Author-email: ak@alkov.pro
License: MIT
Download-URL: https://github.com/devopshq/crosspm.git
Keywords: development,dependency,requirements,manager,versioning,packet
Platform: UNKNOWN
Classifier: Development Status :: 5 - Production/Stable
Classifier: Environment :: Console
Classifier: Intended Audience :: Developers
Classifier: Topic :: Software Development :: Build Tools
Classifier: License :: OSI Approved :: MIT License
Classifier: Natural Language :: English
Classifier: Programming Language :: Python :: 3
Classifier: Programming Language :: Python :: 3.8
Classifier: Programming Language :: Python :: 3.9
Classifier: Programming Language :: Python :: 3.10
Classifier: Programming Language :: Python :: 3.11
Requires-Python: >=3.8.0
Requires-Dist: requests (<3.0.0,>=2.30.0)
Requires-Dist: urllib3 (>=2.2.0)
Requires-Dist: docopt (==0.6.2)
Requires-Dist: PyYAML (>=6.0)
Requires-Dist: dohq-artifactory (>=0.8.3)
Requires-Dist: Jinja2 (>=3.1.3)
Requires-Dist: patool (==1.12)
Requires-Dist: pyunpack (==0.2)
